Topsis/__init__.py
Topsis/__main__.py
Topsis_Abhinandan_102103110-0.0.1.dist-info/METADATA
Topsis_Abhinandan_102103110-0.0.1.dist-info/WHEEL
Topsis_Abhinandan_102103110-0.0.1.dist-info/entry_points.txt
Topsis_Abhinandan_102103110-0.0.1.dist-info/top_level.txt
Topsis_Abhinandan_102103110-0.0.1.dist-info/RECORD
