Metadata-Version: 2.1
Name: Topsis-Abhinandan-102103110
Version: 0.0.1
Summary: Topsis-Abhinandan-102103110
Home-page: https://github.com/Abhinandan2003/Topsis-Abhinandan-102103110
Author: Abhinandan Sharma
Author-email: sabhi2003@gmail.com
License: MIT
Classifier: License :: OSI Approved :: MIT License
Classifier: Programming Language :: Python :: 3.6
Classifier: Programming Language :: Python :: 3.7
Classifier: Programming Language :: Python :: 3.8
